atcociftogtfs/__init__.py
atcociftogtfs/__main__.py
atcociftogtfs/atcocif.py
atcociftogtfs/loader.py
atcociftogtfs-2021.1.31.dist-info/LICENSE.md
atcociftogtfs-2021.1.31.dist-info/METADATA
atcociftogtfs-2021.1.31.dist-info/WHEEL
atcociftogtfs-2021.1.31.dist-info/entry_points.txt
atcociftogtfs-2021.1.31.dist-info/top_level.txt
atcociftogtfs-2021.1.31.dist-info/RECORD
