Metadata-Version: 2.1
Name: atcociftogtfs
Version: 2021.1.31
Summary: Converts ATCO.CIF public transport schedules into GTFS
Home-page: https://github.com/timhowgego/atcociftogtfs
Author: Tim Howgego
Author-email: timothyhowgego@gmail.com
License: MIT
Platform: UNKNOWN
Classifier: Programming Language :: Python :: 3
Classifier: License :: OSI Approved :: MIT License
Classifier: Operating System :: OS Independent
Requires-Python: >=3.3
Requires-Dist: pyproj
